datasette_socrata/__init__.py
datasette_socrata/templates/datasette_socrata.html
datasette_socrata/templates/datasette_socrata_error.html
datasette_socrata-0.3.1.dist-info/LICENSE
datasette_socrata-0.3.1.dist-info/METADATA
datasette_socrata-0.3.1.dist-info/WHEEL
datasette_socrata-0.3.1.dist-info/entry_points.txt
datasette_socrata-0.3.1.dist-info/top_level.txt
datasette_socrata-0.3.1.dist-info/RECORD
