Metadata-Version: 2.1
Name: datasette-socrata
Version: 0.3.1
Summary: Import data from Socrata into Datasette
Home-page: https://github.com/simonw/datasette-socrata
Author: Simon Willison
License: Apache License, Version 2.0
Project-URL: Issues, https://github.com/simonw/datasette-socrata/issues
Project-URL: CI, https://github.com/simonw/datasette-socrata/actions
Project-URL: Changelog, https://github.com/simonw/datasette-socrata/releases
Classifier: Framework :: Datasette
Classifier: License :: OSI Approved :: Apache Software License
Requires-Python: >=3.7
License-File: LICENSE
Requires-Dist: datasette
Requires-Dist: sqlite-utils (>=3.27)
Requires-Dist: datasette-low-disk-space-hook
Provides-Extra: test
Requires-Dist: pytest ; extra == 'test'
Requires-Dist: pytest-asyncio ; extra == 'test'
Requires-Dist: pytest-httpx ; extra == 'test'
